fingerprintmatcher.py
fingerprintMatcher-1.0.6.dist-info/METADATA
fingerprintMatcher-1.0.6.dist-info/WHEEL
fingerprintMatcher-1.0.6.dist-info/top_level.txt
fingerprintMatcher-1.0.6.dist-info/RECORD
