Metadata-Version: 2.1
Name: fingerprintMatcher
Version: 1.0.6
Summary: The FingerprintMatcher Python package provides a comprehensive toolkit for fingerprint matching and recognition tasks. With its intuitive interface and powerful functionality, this package enables users to compare fingerprint images, match them against a database of known fingerprints, and determine their similarity with high accuracy.
Home-page: https://github.com/Tharunk07/fingerprintMatcher
Author: Tharun K
Author-email: tharunkkumarasamy@gmail.com
Project-URL: Bug Tracker, https://github.com/Tharunk07/fingerprintMatcher/issues
Classifier: Programming Language :: Python :: 3
Classifier: License :: OSI Approved :: MIT License
Classifier: Operating System :: OS Independent
Requires-Dist: opencv-python >=4.9.0
Requires-Dist: opencv-contrib-python
